mikeapted_myconstruct/__init__.py
mikeapted_myconstruct/py.typed
mikeapted_myconstruct/_jsii/__init__.py
mikeapted_myconstruct/_jsii/my-construct@0.1.0.jsii.tgz
mikeapted_myconstruct-0.1.0.dist-info/LICENSE
mikeapted_myconstruct-0.1.0.dist-info/METADATA
mikeapted_myconstruct-0.1.0.dist-info/WHEEL
mikeapted_myconstruct-0.1.0.dist-info/top_level.txt
mikeapted_myconstruct-0.1.0.dist-info/RECORD
