Metadata-Version: 2.1
Name: mikeapted-myconstruct
Version: 0.1.0
Summary: my-construct
Home-page: https://www.github.com/mikeapted/my-construct.git
Author: Mike Apted<hello@me.com>
License: MIT
Project-URL: Source, https://www.github.com/mikeapted/my-construct.git
Platform: UNKNOWN
Classifier: Intended Audience :: Developers
Classifier: Operating System :: OS Independent
Classifier: Programming Language :: JavaScript
Classifier: Programming Language :: Python :: 3 :: Only
Classifier: Programming Language :: Python :: 3.6
Classifier: Programming Language :: Python :: 3.7
Classifier: Programming Language :: Python :: 3.8
Classifier: Programming Language :: Python :: 3.9
Classifier: Typing :: Typed
Classifier: Development Status :: 4 - Beta
Classifier: License :: OSI Approved
Requires-Python: >=3.6
Requires-Dist: aws-cdk.aws-apigateway (==1.116.0)
Requires-Dist: aws-cdk.aws-lambda (==1.116.0)
Requires-Dist: aws-cdk.core (==1.116.0)
Requires-Dist: constructs (<4.0.0,>=3.3.69)
Requires-Dist: jsii (<2.0.0,>=1.32.0)
Requires-Dist: publication (>=0.0.3)
